.gitignore
.travis.yml
LICENSE
VERSION
requirements.txt
setup.py
setup_requirements.txt
test_requirements.txt
examples/configyamlwithenv.py
logging_yamlconfig/__init__.py
logging_yamlconfig/configloader.py
logging_yamlconfig.egg-info/PKG-INFO
logging_yamlconfig.egg-info/SOURCES.txt
logging_yamlconfig.egg-info/dependency_links.txt
logging_yamlconfig.egg-info/requires.txt
logging_yamlconfig.egg-info/top_level.txt