Metadata-Version: 1.1
Name: logging-yamlconfig
Version: 0.1.4
Summary: Python dictconfig helpers for yaml config files
Home-page: https://github.com/dyejon/python_logging_yamlconfig
Author: IBM
Author-email: jdye@us.ibm.com
License: UNKNOWN
Download-URL: https://github.com/dyejon/python_logging_yamlconfig/tarball/0.1.4
Platform: UNKNOWN
Provides: logging_yamlconfig
